sadm.py
_sadm/__init__.py
_sadm/_version.py
_sadm/_version_build.py
_sadm/asset.py
_sadm/build.py
_sadm/cfg.py
_sadm/dist.py
_sadm/errors.py
_sadm/libdir.py
_sadm/log.py
_sadm/version.py
_sadm/cmd/__init__.py
_sadm/cmd/build.py
_sadm/cmd/devops.py
_sadm/cmd/flags.py
_sadm/cmd/listen.py
_sadm/cmd/web.py
_sadm/cmd/deploy/__init__.py
_sadm/cmd/deploy/deploy.py
_sadm/cmd/deploy/loader.py
_sadm/configure/__init__.py
_sadm/configure/plugins.py
_sadm/deploy/__init__.py
_sadm/deploy/cmd.py
_sadm/deploy/extractor.py
_sadm/deploy/loader.py
_sadm/deploy/self_extract.py
_sadm/devops/__init__.py
_sadm/devops/devel.py
_sadm/devops/devops.py
_sadm/devops/wapp/__init__.py
_sadm/devops/wapp/cfg.py
_sadm/devops/wapp/errors.py
_sadm/devops/wapp/handlers.py
_sadm/devops/wapp/user.py
_sadm/devops/wapp/wapp.conf
_sadm/devops/wapp/wapp.py
_sadm/devops/wapp/auth/__init__.py
_sadm/devops/wapp/auth/auth.py
_sadm/devops/wapp/auth/config.py
_sadm/devops/wapp/auth/error.py
_sadm/devops/wapp/auth/sslcert.py
_sadm/devops/wapp/plugin/__init__.py
_sadm/devops/wapp/plugin/auth.py
_sadm/devops/wapp/session/__init__.py
_sadm/devops/wapp/session/db.py
_sadm/devops/wapp/session/session.py
_sadm/devops/wapp/static/__init__.py
_sadm/devops/wapp/static/default.css
_sadm/devops/wapp/static/favicon.ico
_sadm/devops/wapp/static/logo.png
_sadm/devops/wapp/static/static.py
_sadm/devops/wapp/static/w3css/4/w3.css
_sadm/devops/wapp/tpl/__init__.py
_sadm/devops/wapp/tpl/base.html
_sadm/devops/wapp/tpl/errors.html
_sadm/devops/wapp/tpl/footer.html
_sadm/devops/wapp/tpl/header.html
_sadm/devops/wapp/tpl/index.html
_sadm/devops/wapp/tpl/navbar-items.html
_sadm/devops/wapp/tpl/navbar.html
_sadm/devops/wapp/tpl/tpl.py
_sadm/devops/wapp/tpl/repo/info.html
_sadm/devops/wapp/tpl/user/home.html
_sadm/devops/wapp/tpl/user/login.html
_sadm/devops/wapp/view/__init__.py
_sadm/devops/wapp/view/index.py
_sadm/devops/wapp/view/view.py
_sadm/devops/wapp/view/user/__init__.py
_sadm/devops/wapp/view/user/auth.py
sadm-0.21.dist-info/LICENSE
sadm-0.21.dist-info/METADATA
sadm-0.21.dist-info/WHEEL
sadm-0.21.dist-info/entry_points.txt
sadm-0.21.dist-info/top_level.txt
sadm-0.21.dist-info/RECORD
