Metadata-Version: 2.1
Name: sadm
Version: 0.21
Summary: sysadmin/devops/deploy tools
Home-page: https://pypi.org/project/sadm
Author: Jeremías Casteglione
Author-email: jrmsdev@gmail.com
License: BSD
Project-URL: Source, https://github.com/jrmsdev/pysadm
Project-URL: Tracker, https://github.com/jrmsdev/pysadm/issues
Keywords: sysadmin,devops,deploy
Platform: linux
Classifier: Development Status :: 4 - Beta
Classifier: Intended Audience :: Developers
Classifier: Intended Audience :: System Administrators
Classifier: Topic :: Software Development :: Build Tools
Classifier: License :: OSI Approved :: BSD License
Classifier: Operating System :: POSIX :: Linux
Classifier: Programming Language :: Python :: 3
Classifier: Programming Language :: Python :: 3.6
Classifier: Programming Language :: Python :: 3.7
Requires-Python: ~=3.6
Requires-Dist: bottle (==0.12.17)
